{
  "1": {
    "7:30": "[📱Заочне] Заплановані пари на сьогодні (понеділок):\n\n8:00 — Математика (Воробйова А.В.)\n9:30 — Інформатика (Залецька І.О.)\n11:20 — Комп'ютерне проєктування (Максимов О.С.)\n15:40 — [НЕ ОБОВ'ЯЗКОВО] Консультація з математики (Воробйова А.В.)",
    "7:58": "Математика (Воробйова А.В.)\nhttps://us02web.zoom.us/j/7142657607?pwd=TlRsMFYxbmFVVWt5b2lUVDJvbytzQT09|961384484->2471",
    "9:28": "Інформатика (Залецька І.О.)\nhttps://us04web.zoom.us/j/6986008668?pwd=Qk4WcDE1Z1AHHJn0elz8DI7EiizeR3.1",
    "11:18": "Комп'ютерне проєктування (Максимов О.С.)\nhttps://us05web.zoom.us/j/3034350821?pwd=WEtHK0llaWZmTWtmTnhPUlVqRmlGUT09",
    "15:38": "[НЕ ОБОВ'ЯЗКОВО] Консультація з математики (Воробйова А.В.)\nhttps://us02web.zoom.us/j/7142657607?pwd=TlRsMFYxbmFVVWt5b2lUVDJvbytzQT09"
  },
  "2": {
    "7:30": "[🚶🏻️Очне] Заплановані пари на сьогодні (вівторок):\n\n8:00 — Історія: Україна і світ (Левченко Г.С.)\n9:30 — Фізика (Тюрин О.В.)\n11:20 — Українська література (Задорожна М.О.)",
    "7:58": "Історія: Україна і світ (Левченко Г.С.)\nhttps://us02web.zoom.us/j/89583152783?pwd=ZDhDYjhtdkdDK2tmSy9zMFlNMUZyQT09|961384484->2470",
    "9:28": "Фізика (Тюрин О.В.)\nhttps://us02web.zoom.us/j/8286799542?pwd=VUdqRXpuQVdwaVNXRjdseFN2YzZNZz09|961384484->2472",
    "11:18": "Українська література (Задорожна М.О.)\nhttps://us04web.zoom.us/j/8481963852?pwd=UHVyUFNCbU4wSlhoNnlMUGNmQkl2QT09"
  },
  "3": {
    "7:30": "[🚶🏻️Очне] Заплановані пари на сьогодні (середа):\n\n8:00 — Математичний аналіз (Тюрин О.В.)\n9:30 — Математичний аналіз (Тюрин О.В.)\n11:20 — Біологія (Ткаченко М.В.)\n12:50 — Математика (Воробйова А.В.)",
    "7:58": "Математичний аналіз (Тюрин О.В.)\nhttps://us02web.zoom.us/j/8286799542?pwd=VUdqRXpuQVdwaVNXRjdseFN2YzZNZz09",
    "9:28": "Математичний аналіз (Тюрин О.В.)\nhttps://us02web.zoom.us/j/8286799542?pwd=VUdqRXpuQVdwaVNXRjdseFN2YzZNZz09",
    "11:20": "Біологія (Ткаченко М.В.)\nhttps://us04web.zoom.us/j/2296510854?pwd=aVgvdUJNRVNiU3pTdzI0Rytza2UrQT09",
    "12:48": "Математика (Воробйова А.В.)\nhttps://us02web.zoom.us/j/7142657607?pwd=TlRsMFYxbmFVVWt5b2lUVDJvbytzQT09|961384484->2471"
  },
  "4": {
    "7:30": "[🚶🏻️Очне] Заплановані пари на сьогодні (четвер):\n\n8:00 — Історія: Україна і світ (Левченко Г.С.)\n9:30 — Англійська мова (Бондар К.С.)\n11:20 — Українська мова (Задорожна М.О.)",
    "7:58": "Історія: Україна і світ (Левченко Г.С.)\nhttps://us02web.zoom.us/j/89583152783?pwd=ZDhDYjhtdkdDK2tmSy9zMFlNMUZyQT09|961384484->2470",
    "9:28": "Англійська мова (Бондар К.С.)\nhttps://us04web.zoom.us/j/79613935928?pwd=lY1eDmkdQ7QJ7bQHo6dshWwwabvpCK.1",
    "11:18": "Українська мова (Задорожна М.О.)\nhttps://us04web.zoom.us/j/8481963852?pwd=UHVyUFNCbU4wSlhoNnlMUGNmQkl2QT09"
  },
  "5": {
    "7:30": "[📱Заочне] Заплановані пари на сьогодні (п'ятниця):\n\n8:00 — Фізичне виховання (Терещенко О.В.)\n9:30 — Укр.мова за проф.спрямуванням (Задорожна М.О.)\n11:20 — Зарубіжна література (Задорожна М.О.)\n12:50 — Географія (Нефедова Н.Є.)",
    "7:58": "Фізичне виховання (Терещенко О.В.)\nhttps://us05web.zoom.us/j/4858060925?pwd=RUEvYnBObTlYb25lRTNrMUYvNG1Qdz09",
    "9:28": "Укр.мова за проф.спрямуванням (Задорожна М.О.)\nhttps://us04web.zoom.us/j/8481963852?pwd=UHVyUFNCbU4wSlhoNnlMUGNmQkl2QT09",
    "11:18": "Зарубіжна література (Задорожна М.О.)\nhttps://us04web.zoom.us/j/8481963852?pwd=UHVyUFNCbU4wSlhoNnlMUGNmQkl2QT09",
    "12:48": "Географія (Нефедова Н.Є.)\nhttps://us05web.zoom.us/j/6275618917?pwd=V2tXTndHbW1kdlZVOHRCT3VLQ2N5Zz09"
  }
}
